android_useful_adb/__init__.py
android_useful_adb/settings.py
android_useful_adb/useful_adb.py
android_useful_adb/libs/__init__.py
android_useful_adb/libs/_aapt.py
android_useful_adb/libs/adb_base.py
android_useful_adb/libs/android_dom.py
android_useful_adb/libs/apk.py
android_useful_adb/libs/command.py
android_useful_adb/libs/keyevent.py
android_useful_adb/libs/perf/__init__.py
android_useful_adb/libs/perf/cpu_and_memery.py
android_useful_adb/libs/perf/fps.py
android_useful_adb/libs/perf/launch.py
android_useful_adb/static/mac/aapt
android_useful_adb/static/mac/adb
android_useful_adb/static/windows/AdbWinApi.dll
android_useful_adb/static/windows/AdbWinUsbApi.dll
android_useful_adb/static/windows/aapt.exe
android_useful_adb/static/windows/adb.exe
android_useful_adb-0.0.4.dist-info/LICENSE.txt
android_useful_adb-0.0.4.dist-info/METADATA
android_useful_adb-0.0.4.dist-info/WHEEL
android_useful_adb-0.0.4.dist-info/top_level.txt
android_useful_adb-0.0.4.dist-info/RECORD
