Metadata-Version: 2.1
Name: android_useful_adb
Version: 0.0.4
Summary: 常用adb命令
Home-page: https://github.com/LiNoZues/useful_adb
Author: Cxz
Author-email: chenzhe12320@163.com
Keywords: ADB adb android
Classifier: Programming Language :: Python :: 3
Classifier: License :: OSI Approved :: MIT License
Classifier: Operating System :: OS Independent
Requires-Python: >=3.6
License-File: LICENSE.txt
Requires-Dist: AxmlParserPY ==0.0.4
Requires-Dist: bytecode ==0.15.1
Requires-Dist: loguru ==0.7.2
